setup.py
Flask_Components.egg-info/PKG-INFO
Flask_Components.egg-info/SOURCES.txt
Flask_Components.egg-info/dependency_links.txt
Flask_Components.egg-info/requires.txt
Flask_Components.egg-info/top_level.txt
src/flask_components/__init__.py
src/flask_components/_version.py
src/flask_components/utils.py